uec/__init__.py
unified_entity_card-0.1.1.dist-info/METADATA
unified_entity_card-0.1.1.dist-info/WHEEL
unified_entity_card-0.1.1.dist-info/top_level.txt
unified_entity_card-0.1.1.dist-info/RECORD
