Metadata-Version: 2.4
Name: unified-entity-card
Version: 0.1.1
Summary: Unified Entity Card helpers
License: MIT
Requires-Python: >=3.9
